RpiSerial/RpiSerial.py
RpiSerial/__init__.py
RpiSerial-0.0.2.dist-info/LICENSE
RpiSerial-0.0.2.dist-info/METADATA
RpiSerial-0.0.2.dist-info/WHEEL
RpiSerial-0.0.2.dist-info/top_level.txt
RpiSerial-0.0.2.dist-info/RECORD
